ius_time/__init__.py
ius_time/cli/__init__.py
ius_time/cli/end_tasks.py
ius_time/cli/lists.py
ius_time/cli/main.py
ius_time/db.py
ius_time/filters.py
ius_time/table_outputs.py
ius_time/utils.py
ius_time-0.2.0.dist-info/LICENSE
ius_time-0.2.0.dist-info/METADATA
ius_time-0.2.0.dist-info/WHEEL
ius_time-0.2.0.dist-info/entry_points.txt
ius_time-0.2.0.dist-info/RECORD
