Metadata-Version: 2.1
Name: ius-time
Version: 0.2.0
Summary: Time tracking CLI application written in Python
Home-page: https://github.com/mrasore98/ius-time
License: GPL-3.0-or-later
Author: Mathias Alexander
Author-email: mathias.alexander@irhythmtech.com
Requires-Python: >=3.12,<4.0
Classifier: License :: OSI Approved :: GNU General Public License v3 or later (GPLv3+)
Classifier: Programming Language :: Python :: 3
Classifier: Programming Language :: Python :: 3.12
Classifier: Programming Language :: Python :: 3.13
Requires-Dist: heliclockter (>=1.3.0,<2.0.0)
Requires-Dist: sqlmodel (>=0.0.24,<0.0.25)
Requires-Dist: typer[all] (>=0.12.3,<0.13.0)
Requires-Dist: tzdata (>=2024.1,<2025.0)
Project-URL: Repository, https://github.com/mrasore98/ius-time
